{
    "version": "https://jsonfeed.org/version/1",
    "title": "Akash Patki",
    "home_page_url": "https://keycache.github.io/",
    "feed_url": "https://keycache.github.io/feed.json",
    "description": "A showcase for a Toronto-based full-stack developer with 15+ years of experience across startups, scale-ups, and big banks.",
    "items": [
        {
            "id": "https://keycache.github.io/blog/2025-08-01-encoding-hashing-encryption",
            "content_html": "How does your digital information stay safe and compatible with online sysstems? Understanding the core differences between encoding, hashing, and encryption is crucial for every software engineer.",
            "url": "https://keycache.github.io/blog/2025-08-01-encoding-hashing-encryption",
            "title": "Core Idea Behing Encoding, Hashing, and Encryption",
            "date_modified": "2025-08-07T00:00:00.000Z",
            "tags": [
                "encoding",
                "hashing",
                "encryption",
                "fundamentals"
            ]
        },
        {
            "id": "https://keycache.github.io/blog/four-faces-of-a-developer",
            "content_html": "Every developer juggles at least four identities — polished pro, clueless explainer, chill buddy, and masked internet gremlin — depending on who's watching",
            "url": "https://keycache.github.io/blog/four-faces-of-a-developer",
            "title": "The Four Faces of a Developer: Why Every Dev Has (At Least) 4 Personalities",
            "date_modified": "2025-07-04T00:00:00.000Z",
            "tags": [
                "dev-life",
                "personas",
                "programming"
            ]
        },
        {
            "id": "https://keycache.github.io/blog/polymorpism-in-python",
            "content_html": "Polymorphism sounds complex, but it’s easier (and cooler) than you think. Let a cartoon snake walk you through writing cleaner Python code.",
            "url": "https://keycache.github.io/blog/polymorpism-in-python",
            "title": "No More `if isinstance`— Polymorphism in Python with `@singledispatch`!",
            "date_modified": "2025-07-15T00:00:00.000Z",
            "tags": [
                "python",
                "programming",
                "oop",
                "polymorphism"
            ]
        },
        {
            "id": "https://keycache.github.io/blog/when-you-are-the-judge-and-contestant-for-your-and-thei-ideas",
            "content_html": "You’re in a team meeting, two ideas clash, and yours is one of them. How do you stay fair, thoughtful, and not spiral into self-doubt? Here's a relatable deep dive into the mental gymnastics of honest decision-making.",
            "url": "https://keycache.github.io/blog/when-you-are-the-judge-and-contestant-for-your-and-thei-ideas",
            "title": "When You’re the Judge and the Contestant for your and their ideas.",
            "date_modified": "2025-07-31T00:00:00.000Z",
            "tags": [
                "leadership",
                "decision-making",
                "bias",
                "team-culture",
                "self-doubt",
                "growth"
            ]
        }
    ]
}